development/demo.py
development/demov6.py
development/test.py
tkfontawesome/__init__.py
tkfontawesome/svgs.py
tkfontawesome/svgs/consolidate.py
tkfontawesome-0.3.2.dist-info/licenses/LICENSE
tkfontawesome-0.3.2.dist-info/METADATA
tkfontawesome-0.3.2.dist-info/WHEEL
tkfontawesome-0.3.2.dist-info/top_level.txt
tkfontawesome-0.3.2.dist-info/RECORD
