Metadata-Version: 2.4
Name: tkfontawesome
Version: 0.3.2
Summary: Use any of the 2k+ free FontAwesome icons in your tkinter application.
Author-email: Israel Dryer <israel.dryer@gmail.com>
License: MIT License
Project-URL: Homepage, https://github.com/israel-dryer/tkfontawesome
Project-URL: Repository, https://github.com/israel-dryer/tkfontawesome
Project-URL: Issues, https://github.com/israel-dryer/tkfontawesome/issues
Keywords: svg,fontawesome,icons,tkinter,ttk
Classifier: Programming Language :: Python :: 3
Classifier: License :: OSI Approved :: MIT License
Classifier: Operating System :: OS Independent
Requires-Python: >=3.8
License-File: LICENSE
Requires-Dist: lxml<6.0.0,>=5.4.0
Requires-Dist: tksvg<0.8.0,>=0.7.4
Dynamic: license-file
